scm203lab267100370/__init__.py
scm203lab267100370/lab2mod167100370.py
scm203lab267100370/lab2mod267100370.py
scm203lab267100370-0.1.1.dist-info/METADATA
scm203lab267100370-0.1.1.dist-info/WHEEL
scm203lab267100370-0.1.1.dist-info/top_level.txt
scm203lab267100370-0.1.1.dist-info/RECORD
