Metadata-Version: 2.4
Name: scm203lab267100370
Version: 0.1.1
Summary: This my package. Can use to Roots of Equation in One Variable and Initial Value Problems for a frist-order differential equation 
Home-page: https://github.com/Cartoonmee/scm203lab267100370
Author: THITIRAT
Author-email: thitirat98242@gmail.com
Requires-Python: >=3.7
Dynamic: author
Dynamic: author-email
Dynamic: description
Dynamic: description-content-type
Dynamic: home-page
Dynamic: requires-python
Dynamic: summary
